turu/core/__init__.py
turu/core/async_connection.py
turu/core/async_cursor.py
turu/core/connection.py
turu/core/cursor.py
turu/core/exception.py
turu/core/features.py
turu/core/mock/__init__.py
turu/core/mock/async_connection.py
turu/core/mock/async_cursor.py
turu/core/mock/connection.py
turu/core/mock/cursor.py
turu/core/mock/exception.py
turu/core/mock/store.py
turu/core/protocols/__init__.py
turu/core/protocols/async_connection.py
turu/core/protocols/async_cursor.py
turu/core/protocols/connection.py
turu/core/protocols/cursor.py
turu/core/protocols/dataclass.py
turu/core/py.typed
turu/core/record/__init__.py
turu/core/record/async_record_cursor.py
turu/core/record/csv_recorder.py
turu/core/record/record_cursor.py
turu/core/record/recorder_protcol.py
turu/core/tag.py
turu_core-0.13.2.dist-info/METADATA
turu_core-0.13.2.dist-info/WHEEL
turu_core-0.13.2.dist-info/RECORD
